simspace/__init__.py
simspace/core.py
simspace/niche.py
simspace/omics.py
simspace/optimize.py
simspace/plot.py
simspace/spatial.py
simspace/util.py
simspace/R/.Rprofile
simspace/R/SRTsim.R
simspace/R/install_r_deps.R
simspace/R/renv.lock
simspace/R/scdesign.R
simspace/R/splatter.R
simspace/R/splatter_fit.R
simspace/R/renv/activate.R
simspace/initialize/initialize.py
simspace/initialize/neighbors.py
simspace-0.2.6.dist-info/licenses/LICENSE
simspace-0.2.6.dist-info/METADATA
simspace-0.2.6.dist-info/WHEEL
simspace-0.2.6.dist-info/top_level.txt
simspace-0.2.6.dist-info/RECORD
