Metadata-Version: 2.4
Name: simspace
Version: 0.2.6
Summary: SimSpace: a comprehensive in-silico spatial omics data simulation framework
Author: Tianxiao Zhao
License: MIT
Requires-Python: >=3.10
License-File: LICENSE
Requires-Dist: numpy>=2.2.6
Requires-Dist: scipy>=1.15.2
Requires-Dist: pandas>=2.3.1
Requires-Dist: matplotlib>=3.10.3
Requires-Dist: seaborn>=0.13.2
Requires-Dist: scikit-learn>=1.7.0
Requires-Dist: colorcet>=3.1.0
Requires-Dist: esda>=2.7.1
Requires-Dist: libpysal>=4.12.1
Provides-Extra: dev
Requires-Dist: pytest; extra == "dev"
Dynamic: license-file
Dynamic: requires-python
